{
  "rankInformation": {
    "name": "Tenderfoot",
    "rankId": 2,
    "version": "2022",
    "expiredDate": "",
    "versionEffectiveDt": "2022-08-01",
    "versionExpiryDt": "",
    "short": "Tenderfoot",
    "reallyShort": "Tenderfoot",
    "level": "2",
    "image": "tenderfoot.png",
    "programId": "2",
    "searchKeywords": "Boy Scout Scouting Tenderfoot Rank Award Requirements",
    "lds": "True",
    "sku": "657437",
    "price": "2.99",
    "priceLastUpdated": "2013-12-16",
    "scoutNet": "RT",
    "header": "",
    "footer": "<strong>NOTES:</strong>  The requirements for Scout, Tenderfoot, Second Class, and First Class ranks may be worked on simultaneously; however, these ranks must be earned in sequence.<br><br/>\r\nAlternative requirements for the Scout rank are available for Scouts with physical or mental disabilities if they meet the criteria listed in the Scouts BSA Requirements book.",
    "adminNotes": "",
    "proofReadDate": "",
    "active": "True",
    "disabledOnQuickEntry": "False",
    "imageUrl100": "https://d1kn0x9vzr5n76.cloudfront.net/images/ranks/tenderfoot100.png",
    "imageUrl200": "https://d1kn0x9vzr5n76.cloudfront.net/images/ranks/tenderfoot200.png",
    "imageUrl400": "https://d1kn0x9vzr5n76.cloudfront.net/images/ranks/tenderfoot400.png"
  },
  "requirements": [
    {
      "id": "1980",
      "versionId": "83",
      "name": "Present yourself to your leader, prepared for an overnight camping trip. Show the personal and camping gear you will use. Show the right way to pack and carry it.",
      "short": "Prepare to camp",
      "listNumber": "1a.",
      "requirementNumber": "1a",
      "sortOrder": "1.1",
      "footer": "",
      "childrenRequired": "",
      "required": "True",
      "parentRequirementId": "",
      "videoExternalURLId": "",
      "previousRankRequired": "False",
      "monthsSinceLastRankRequired": "",
      "eagleMBRequired": "",
      "totalMBRequired": "",
      "serviceHoursRequired": "",
      "disabledOnQuickEntry": "False",
      "linkedAdventureId": "",
      "linkedAwardId": "",
      "linkedAdventure": {},
      "electiveAdventure": false,
      "linkedElectiveAdventures": [],
      "requiresSSElective": false,
      "ssElectives": []
    },
    {
      "id": "1981",
      "versionId": "83",
      "name": "Record your best in the following tests:<br>\r\n<br><strong>Current results</strong><br>\r\n<ul class=\"li-none\">\r\n  <li>Push-ups ________ (Record the number done correctly in 60 seconds)</li>\r\n  <li>Sit-ups or curl-ups________ (Record the number done correctly in 60 seconds)</li>\r\n <li>Back-saver sit-and-reach _________ (Record the distance stretched)</li>\r\n  <li>1 mile walk/run _____________ (record the time)</li>\r\n</ul>\r\n",
      "short": "Fitness benchmark",
      "listNumber": "6a.",
      "requirementNumber": "6a",
      "sortOrder": "6.1",
      "footer": "",
      "childrenRequired": "",
      "required": "True",
      "parentRequirementId": "",
      "videoExternalURLId": "",
      "previousRankRequired": "False",
      "monthsSinceLastRankRequired": "",
      "eagleMBRequired": "",
      "totalMBRequired": "",
      "serviceHoursRequired": "",
      "disabledOnQuickEntry": "False",
      "linkedAdventureId": "",
      "linkedAwardId": "",
      "linkedAdventure": {},
      "electiveAdventure": false,
      "linkedElectiveAdventures": [],
      "requiresSSElective": false,
      "ssElectives": []
    },
    {
      "id": "1982",
      "versionId": "83",
      "name": "Describe common poisonous or hazardous plants; identify any that grow in your local area or campsite location. Tell how to treat for exposure to them.",
      "short": "Poisonous plants",
      "listNumber": "4b.",
      "requirementNumber": "4b",
      "sortOrder": "4.2",
      "footer": "",
      "childrenRequired": "",
      "required": "True",
      "parentRequirementId": "",
      "videoExternalURLId": "",
      "previousRankRequired": "False",
      "monthsSinceLastRankRequired": "",
      "eagleMBRequired": "",
      "totalMBRequired": "",
      "serviceHoursRequired": "",
      "disabledOnQuickEntry": "False",
      "linkedAdventureId": "",
      "linkedAwardId": "",
      "linkedAdventure": {},
      "electiveAdventure": false,
      "linkedElectiveAdventures": [],
      "requiresSSElective": false,
      "ssElectives": []
    },
    {
      "id": "1983",
      "versionId": "83",
      "name": "Show first aid for the following:\r\n<ul class=\"li-disc\">\r\n  <li>Simple cuts and scrapes</li>\r\n  <li>Blisters on the hand and foot</li>\r\n  <li>Minor (thermal/heat) burns or scalds (superficial, or first-degree)</li>\r\n  <li>Bites or stings of insects and ticks</li>\r\n  <li>Venomous snakebite</li>\r\n  <li>Nosebleed</li>\r\n  <li>Frostbite and sunburn</li>\r\n<li>Choking</li>\r\n</ul>\r\n",
      "short": "First Aid",
      "listNumber": "4a.",
      "requirementNumber": "4a",
      "sortOrder": "4.1",
      "footer": "",
      "childrenRequired": "",
      "required": "True",
      "parentRequirementId": "",
      "videoExternalURLId": "",
      "previousRankRequired": "False",
      "monthsSinceLastRankRequired": "",
      "eagleMBRequired": "",
      "totalMBRequired": "",
      "serviceHoursRequired": "",
      "disabledOnQuickEntry": "False",
      "linkedAdventureId": "",
      "linkedAwardId": "",
      "linkedAdventure": {},
      "electiveAdventure": false,
      "linkedElectiveAdventures": [],
      "requiresSSElective": false,
      "ssElectives": []
    },
    {
      "id": "1984",
      "versionId": "83",
      "name": "Demonstrate Scout spirit by living the Scout Oath and Scout Law. Tell how you have done your duty to God and how you have lived four different points of the Scout Law in your everyday life.",
      "short": "Scout spirit",
      "listNumber": "9.",
      "requirementNumber": "9",
      "sortOrder": "9",
      "footer": "",
      "childrenRequired": "",
      "required": "True",
      "parentRequirementId": "",
      "videoExternalURLId": "",
      "previousRankRequired": "False",
      "monthsSinceLastRankRequired": "",
      "eagleMBRequired": "",
      "totalMBRequired": "",
      "serviceHoursRequired": "",
      "disabledOnQuickEntry": "False",
      "linkedAdventureId": "",
      "linkedAwardId": "",
      "linkedAdventure": {},
      "electiveAdventure": false,
      "linkedElectiveAdventures": [],
      "requiresSSElective": false,
      "ssElectives": []
    },
    {
      "id": "1985",
      "versionId": "83",
      "name": "While working toward the Tenderfoot rank, and after completing Scout rank requirement 7, participate in a Scoutmaster conference.\r\n",
      "short": "Scoutmaster conference",
      "listNumber": "10.",
      "requirementNumber": "10",
      "sortOrder": "10",
      "footer": "",
      "childrenRequired": "",
      "required": "True",
      "parentRequirementId": "",
      "videoExternalURLId": "",
      "previousRankRequired": "False",
      "monthsSinceLastRankRequired": "",
      "eagleMBRequired": "",
      "totalMBRequired": "",
      "serviceHoursRequired": "",
      "disabledOnQuickEntry": "False",
      "linkedAdventureId": "",
      "linkedAwardId": "",
      "linkedAdventure": {},
      "electiveAdventure": false,
      "linkedElectiveAdventures": [],
      "requiresSSElective": false,
      "ssElectives": []
    },
    {
      "id": "1986",
      "versionId": "83",
      "name": "Successfully complete your board of review for the Tenderfoot rank.",
      "short": "Board of review",
      "listNumber": "11.",
      "requirementNumber": "11",
      "sortOrder": "11",
      "footer": "",
      "childrenRequired": "",
      "required": "True",
      "parentRequirementId": "",
      "videoExternalURLId": "",
      "previousRankRequired": "False",
      "monthsSinceLastRankRequired": "",
      "eagleMBRequired": "",
      "totalMBRequired": "",
      "serviceHoursRequired": "",
      "disabledOnQuickEntry": "False",
      "linkedAdventureId": "",
      "linkedAwardId": "",
      "linkedAdventure": {},
      "electiveAdventure": false,
      "linkedElectiveAdventures": [],
      "requiresSSElective": false,
      "ssElectives": []
    },
    {
      "id": "1987",
      "versionId": "83",
      "name": "Spend at least one night on a patrol or troop campout. Sleep in a tent you have helped pitch.",
      "short": "Sleep in tent",
      "listNumber": "1b.",
      "requirementNumber": "1b",
      "sortOrder": "1.2",
      "footer": "",
      "childrenRequired": "",
      "required": "True",
      "parentRequirementId": "",
      "videoExternalURLId": "",
      "previousRankRequired": "False",
      "monthsSinceLastRankRequired": "",
      "eagleMBRequired": "",
      "totalMBRequired": "",
      "serviceHoursRequired": "",
      "disabledOnQuickEntry": "False",
      "linkedAdventureId": "",
      "linkedAwardId": "",
      "linkedAdventure": {},
      "electiveAdventure": false,
      "linkedElectiveAdventures": [],
      "requiresSSElective": false,
      "ssElectives": []
    },
    {
      "id": "1988",
      "versionId": "83",
      "name": "On the campout, assist in preparing one of the meals. Tell why it is important for each patrol member to share in meal preparation and cleanup.",
      "short": "Help cook a meal",
      "listNumber": "2a.",
      "requirementNumber": "2a",
      "sortOrder": "2.1",
      "footer": "",
      "childrenRequired": "",
      "required": "True",
      "parentRequirementId": "",
      "videoExternalURLId": "",
      "previousRankRequired": "False",
      "monthsSinceLastRankRequired": "",
      "eagleMBRequired": "",
      "totalMBRequired": "",
      "serviceHoursRequired": "",
      "disabledOnQuickEntry": "False",
      "linkedAdventureId": "",
      "linkedAwardId": "",
      "linkedAdventure": {},
      "electiveAdventure": false,
      "linkedElectiveAdventures": [],
      "requiresSSElective": false,
      "ssElectives": []
    },
    {
      "id": "1989",
      "versionId": "83",
      "name": "While on a campout, demonstrate an appropriate method of safely cleaning items used to prepare, serve, and eat a meal.",
      "short": "Show cooking safety",
      "listNumber": "2b.",
      "requirementNumber": "2b",
      "sortOrder": "2.1",
      "footer": "",
      "childrenRequired": "",
      "required": "True",
      "parentRequirementId": "",
      "videoExternalURLId": "",
      "previousRankRequired": "False",
      "monthsSinceLastRankRequired": "",
      "eagleMBRequired": "",
      "totalMBRequired": "",
      "serviceHoursRequired": "",
      "disabledOnQuickEntry": "False",
      "linkedAdventureId": "",
      "linkedAwardId": "",
      "linkedAdventure": {},
      "electiveAdventure": false,
      "linkedElectiveAdventures": [],
      "requiresSSElective": false,
      "ssElectives": []
    },
    {
      "id": "1990",
      "versionId": "83",
      "name": "Demonstrate a practical use of two half-hitches.",
      "short": "Two half-hitches",
      "listNumber": "3b.",
      "requirementNumber": "3b",
      "sortOrder": "3.2",
      "footer": "",
      "childrenRequired": "",
      "required": "True",
      "parentRequirementId": "",
      "videoExternalURLId": "",
      "previousRankRequired": "False",
      "monthsSinceLastRankRequired": "",
      "eagleMBRequired": "",
      "totalMBRequired": "",
      "serviceHoursRequired": "",
      "disabledOnQuickEntry": "False",
      "linkedAdventureId": "",
      "linkedAwardId": "",
      "linkedAdventure": {},
      "electiveAdventure": false,
      "linkedElectiveAdventures": [],
      "requiresSSElective": false,
      "ssElectives": []
    },
    {
      "id": "1991",
      "versionId": "83",
      "name": "Demonstrate a practical use of the square knot.",
      "short": "Square knot",
      "listNumber": "3a.",
      "requirementNumber": "3a",
      "sortOrder": "3.1",
      "footer": "",
      "childrenRequired": "",
      "required": "True",
      "parentRequirementId": "",
      "videoExternalURLId": "",
      "previousRankRequired": "False",
      "monthsSinceLastRankRequired": "",
      "eagleMBRequired": "",
      "totalMBRequired": "",
      "serviceHoursRequired": "",
      "disabledOnQuickEntry": "False",
      "linkedAdventureId": "",
      "linkedAwardId": "",
      "linkedAdventure": {},
      "electiveAdventure": false,
      "linkedElectiveAdventures": [],
      "requiresSSElective": false,
      "ssElectives": []
    },
    {
      "id": "1992",
      "versionId": "83",
      "name": "Explain the rules of safe and responsible hiking, both on the highway and cross-country, during the day and at night.",
      "short": "Safe Hiking Rules",
      "listNumber": "5c.",
      "requirementNumber": "5c",
      "sortOrder": "5.3",
      "footer": "",
      "childrenRequired": "",
      "required": "True",
      "parentRequirementId": "",
      "videoExternalURLId": "",
      "previousRankRequired": "False",
      "monthsSinceLastRankRequired": "",
      "eagleMBRequired": "",
      "totalMBRequired": "",
      "serviceHoursRequired": "",
      "disabledOnQuickEntry": "False",
      "linkedAdventureId": "",
      "linkedAwardId": "",
      "linkedAdventure": {},
      "electiveAdventure": false,
      "linkedElectiveAdventures": [],
      "requiresSSElective": false,
      "ssElectives": []
    },
    {
      "id": "1993",
      "versionId": "83",
      "name": "Demonstrate how to display, raise, lower, and fold the American flag.",
      "short": "Flag basics",
      "listNumber": "7a",
      "requirementNumber": "7a",
      "sortOrder": "7.1",
      "footer": "",
      "childrenRequired": "",
      "required": "True",
      "parentRequirementId": "",
      "videoExternalURLId": "",
      "previousRankRequired": "False",
      "monthsSinceLastRankRequired": "",
      "eagleMBRequired": "",
      "totalMBRequired": "",
      "serviceHoursRequired": "",
      "disabledOnQuickEntry": "False",
      "linkedAdventureId": "",
      "linkedAwardId": "",
      "linkedAdventure": {},
      "electiveAdventure": false,
      "linkedElectiveAdventures": [],
      "requiresSSElective": false,
      "ssElectives": []
    },
    {
      "id": "1994",
      "versionId": "83",
      "name": "Explain how you demonstrated the Outdoor Code and Leave No Trace on\r\ncampouts or outings.",
      "short": "Outdoor Code",
      "listNumber": "1c.",
      "requirementNumber": "1c",
      "sortOrder": "1.3",
      "footer": "",
      "childrenRequired": "",
      "required": "True",
      "parentRequirementId": "",
      "videoExternalURLId": "",
      "previousRankRequired": "False",
      "monthsSinceLastRankRequired": "",
      "eagleMBRequired": "",
      "totalMBRequired": "",
      "serviceHoursRequired": "",
      "disabledOnQuickEntry": "False",
      "linkedAdventureId": "",
      "linkedAwardId": "",
      "linkedAdventure": {},
      "electiveAdventure": false,
      "linkedElectiveAdventures": [],
      "requiresSSElective": false,
      "ssElectives": []
    },
    {
      "id": "1995",
      "versionId": "83",
      "name": "Explain the importance of eating together as a patrol.",
      "short": "Explain patrol eating",
      "listNumber": "2c.",
      "requirementNumber": "2c",
      "sortOrder": "2.3",
      "footer": "",
      "childrenRequired": "",
      "required": "True",
      "parentRequirementId": "",
      "videoExternalURLId": "",
      "previousRankRequired": "False",
      "monthsSinceLastRankRequired": "",
      "eagleMBRequired": "",
      "totalMBRequired": "",
      "serviceHoursRequired": "",
      "disabledOnQuickEntry": "False",
      "linkedAdventureId": "",
      "linkedAwardId": "",
      "linkedAdventure": {},
      "electiveAdventure": false,
      "linkedElectiveAdventures": [],
      "requiresSSElective": false,
      "ssElectives": []
    },
    {
      "id": "1996",
      "versionId": "83",
      "name": "Demonstrate a practical use of the taut-line hitch.",
      "short": "Taut-line hitch",
      "listNumber": "3c.",
      "requirementNumber": "3c",
      "sortOrder": "3.3",
      "footer": "",
      "childrenRequired": "",
      "required": "True",
      "parentRequirementId": "",
      "videoExternalURLId": "",
      "previousRankRequired": "False",
      "monthsSinceLastRankRequired": "",
      "eagleMBRequired": "",
      "totalMBRequired": "",
      "serviceHoursRequired": "",
      "disabledOnQuickEntry": "False",
      "linkedAdventureId": "",
      "linkedAwardId": "",
      "linkedAdventure": {},
      "electiveAdventure": false,
      "linkedElectiveAdventures": [],
      "requiresSSElective": false,
      "ssElectives": []
    },
    {
      "id": "1997",
      "versionId": "83",
      "name": "Demonstrate proper care, sharpening, and use of the knife, saw, and ax. Describe when each should be used.",
      "short": "Wood tools",
      "listNumber": "3d.",
      "requirementNumber": "3d",
      "sortOrder": "3.4",
      "footer": "",
      "childrenRequired": "",
      "required": "True",
      "parentRequirementId": "",
      "videoExternalURLId": "",
      "previousRankRequired": "False",
      "monthsSinceLastRankRequired": "",
      "eagleMBRequired": "",
      "totalMBRequired": "",
      "serviceHoursRequired": "",
      "disabledOnQuickEntry": "False",
      "linkedAdventureId": "",
      "linkedAwardId": "",
      "linkedAdventure": {},
      "electiveAdventure": false,
      "linkedElectiveAdventures": [],
      "requiresSSElective": false,
      "ssElectives": []
    },
    {
      "id": "1998",
      "versionId": "83",
      "name": "Tell what you can do while on a campout or other outdoor activity to prevent or reduce the occurrence of injuries or exposure listed in Tenderfoot requirements 4a and 4b.",
      "short": "Injury prevention\t",
      "listNumber": "4c.",
      "requirementNumber": "4c",
      "sortOrder": "4.3",
      "footer": "",
      "childrenRequired": "",
      "required": "True",
      "parentRequirementId": "",
      "videoExternalURLId": "",
      "previousRankRequired": "False",
      "monthsSinceLastRankRequired": "",
      "eagleMBRequired": "",
      "totalMBRequired": "",
      "serviceHoursRequired": "",
      "disabledOnQuickEntry": "False",
      "linkedAdventureId": "",
      "linkedAwardId": "",
      "linkedAdventure": {},
      "electiveAdventure": false,
      "linkedElectiveAdventures": [],
      "requiresSSElective": false,
      "ssElectives": []
    },
    {
      "id": "1999",
      "versionId": "83",
      "name": "Explain the importance of the buddy system as it relates to your personal safety on outings and where you live. Use the buddy system while on a troop or patrol outing.",
      "short": "Buddy system\t",
      "listNumber": "5a.",
      "requirementNumber": "5a",
      "sortOrder": "5.1",
      "footer": "",
      "childrenRequired": "",
      "required": "True",
      "parentRequirementId": "",
      "videoExternalURLId": "",
      "previousRankRequired": "False",
      "monthsSinceLastRankRequired": "",
      "eagleMBRequired": "",
      "totalMBRequired": "",
      "serviceHoursRequired": "",
      "disabledOnQuickEntry": "False",
      "linkedAdventureId": "",
      "linkedAwardId": "",
      "linkedAdventure": {},
      "electiveAdventure": false,
      "linkedElectiveAdventures": [],
      "requiresSSElective": false,
      "ssElectives": []
    },
    {
      "id": "2000",
      "versionId": "83",
      "name": "Assemble a personal first-aid kit to carry with you on future campouts and hikes. Tell how each item in the kit would be used.",
      "short": "First-aid kit",
      "listNumber": "4d.",
      "requirementNumber": "4d",
      "sortOrder": "4.4",
      "footer": "",
      "childrenRequired": "",
      "required": "True",
      "parentRequirementId": "",
      "videoExternalURLId": "",
      "previousRankRequired": "False",
      "monthsSinceLastRankRequired": "",
      "eagleMBRequired": "",
      "totalMBRequired": "",
      "serviceHoursRequired": "",
      "disabledOnQuickEntry": "False",
      "linkedAdventureId": "",
      "linkedAwardId": "",
      "linkedAdventure": {},
      "electiveAdventure": false,
      "linkedElectiveAdventures": [],
      "requiresSSElective": false,
      "ssElectives": []
    },
    {
      "id": "2001",
      "versionId": "83",
      "name": "Describe what to do if you become lost on a hike or campout.",
      "short": "Explain actions if lost",
      "listNumber": "5b.",
      "requirementNumber": "5b",
      "sortOrder": "5.2",
      "footer": "",
      "childrenRequired": "",
      "required": "True",
      "parentRequirementId": "",
      "videoExternalURLId": "",
      "previousRankRequired": "False",
      "monthsSinceLastRankRequired": "",
      "eagleMBRequired": "",
      "totalMBRequired": "",
      "serviceHoursRequired": "",
      "disabledOnQuickEntry": "False",
      "linkedAdventureId": "",
      "linkedAwardId": "",
      "linkedAdventure": {},
      "electiveAdventure": false,
      "linkedElectiveAdventures": [],
      "requiresSSElective": false,
      "ssElectives": []
    },
    {
      "id": "2002",
      "versionId": "83",
      "name": "Develop and describe a plan for improvement in each of the activities listed in Tenderfoot requirement 6a. Keep track of your activity for at least 30 days.",
      "short": "Improvement plan",
      "listNumber": "6b.",
      "requirementNumber": "6b",
      "sortOrder": "6.2",
      "footer": "",
      "childrenRequired": "",
      "required": "True",
      "parentRequirementId": "",
      "videoExternalURLId": "",
      "previousRankRequired": "False",
      "monthsSinceLastRankRequired": "",
      "eagleMBRequired": "",
      "totalMBRequired": "",
      "serviceHoursRequired": "",
      "disabledOnQuickEntry": "False",
      "linkedAdventureId": "",
      "linkedAwardId": "",
      "linkedAdventure": {},
      "electiveAdventure": false,
      "linkedElectiveAdventures": [],
      "requiresSSElective": false,
      "ssElectives": []
    },
    {
      "id": "2003",
      "versionId": "83",
      "name": "Show improvement (of any degree) in each activity listed in Tenderfoot requirement 6a after practicing for 30 days.\r\n<br>\r\n<br><strong>30 days later</strong><br>\r\n<ul class=\"li-none\">\r\n  <li>Push-ups ________ (Record the number done correctly in 60 seconds)</li>\r\n  <li>Sit-ups or curl-ups________ (Record the number done correctly in 60 seconds)<li>\r\n <li>Back-saver sit-and-reach _________ (Record the distance stretched)</li>\r\n  <li>1 mile walk/run _____________ (record the time)</li>\r\n</ul>",
      "short": "Test fitness plan",
      "listNumber": "6c.",
      "requirementNumber": "6c",
      "sortOrder": "6.3",
      "footer": "",
      "childrenRequired": "",
      "required": "True",
      "parentRequirementId": "",
      "videoExternalURLId": "",
      "previousRankRequired": "False",
      "monthsSinceLastRankRequired": "",
      "eagleMBRequired": "",
      "totalMBRequired": "",
      "serviceHoursRequired": "",
      "disabledOnQuickEntry": "False",
      "linkedAdventureId": "",
      "linkedAwardId": "",
      "linkedAdventure": {},
      "electiveAdventure": false,
      "linkedElectiveAdventures": [],
      "requiresSSElective": false,
      "ssElectives": []
    },
    {
      "id": "2004",
      "versionId": "83",
      "name": "Participate in a total of one hour of service in one or more service projects approved by your Scoutmaster. Explain how your service to others relates to the Scout slogan and Scout motto.",
      "short": "Service project",
      "listNumber": "7b.",
      "requirementNumber": "7b",
      "sortOrder": "7.2",
      "footer": "",
      "childrenRequired": "",
      "required": "True",
      "parentRequirementId": "",
      "videoExternalURLId": "",
      "previousRankRequired": "False",
      "monthsSinceLastRankRequired": "",
      "eagleMBRequired": "",
      "totalMBRequired": "",
      "serviceHoursRequired": "",
      "disabledOnQuickEntry": "False",
      "linkedAdventureId": "",
      "linkedAwardId": "",
      "linkedAdventure": {},
      "electiveAdventure": false,
      "linkedElectiveAdventures": [],
      "requiresSSElective": false,
      "ssElectives": []
    },
    {
      "id": "2005",
      "versionId": "83",
      "name": "Describe the steps in Scouting's EDGE method.  Use the Teaching EDGE method to teach another person how to tie the square knot.",
      "short": "EDGE method",
      "listNumber": "8.",
      "requirementNumber": "8",
      "sortOrder": "8",
      "footer": "",
      "childrenRequired": "",
      "required": "True",
      "parentRequirementId": "",
      "videoExternalURLId": "",
      "previousRankRequired": "False",
      "monthsSinceLastRankRequired": "",
      "eagleMBRequired": "",
      "totalMBRequired": "",
      "serviceHoursRequired": "",
      "disabledOnQuickEntry": "False",
      "linkedAdventureId": "",
      "linkedAwardId": "",
      "linkedAdventure": {},
      "electiveAdventure": false,
      "linkedElectiveAdventures": [],
      "requiresSSElective": false,
      "ssElectives": []
    },
    {
      "id": "2028",
      "versionId": "83",
      "name": "Explain why it is important to hike on trails or other durable surfaces, and  give examples of durable surfaces you saw on your outing.",
      "short": "Why it is important to hike on trails",
      "listNumber": "5d.",
      "requirementNumber": "5d",
      "sortOrder": "5.4",
      "footer": "",
      "childrenRequired": "",
      "required": "True",
      "parentRequirementId": "",
      "videoExternalURLId": "",
      "previousRankRequired": "False",
      "monthsSinceLastRankRequired": "",
      "eagleMBRequired": "",
      "totalMBRequired": "",
      "serviceHoursRequired": "",
      "disabledOnQuickEntry": "False",
      "linkedAdventureId": "",
      "linkedAwardId": "",
      "linkedAdventure": {},
      "electiveAdventure": false,
      "linkedElectiveAdventures": [],
      "requiresSSElective": false,
      "ssElectives": []
    }
  ]
}